copycat/__init__.py
copycat/__main__.py
copycat/cli.py
copycat/clipboard_core.py
copycat/data_handlers.py
copycat/desktop_integration.py
copycat/gui.py
copycat/py.typed
copycat/system_tray.py
copycat/template_manager.py
copycat/virtual_keyboard.py
copycat/assets/__init__.py
copycat/assets/icon.png
copycat/assets/logo.png
copycat/resources/__init__.py
copycat/resources/default.conf
copycat/resources/templates.json
copycat_linux-1.0.2.dist-info/licenses/LICENSE
copycat_linux-1.0.2.dist-info/METADATA
copycat_linux-1.0.2.dist-info/WHEEL
copycat_linux-1.0.2.dist-info/entry_points.txt
copycat_linux-1.0.2.dist-info/top_level.txt
copycat_linux-1.0.2.dist-info/RECORD
