Metadata-Version: 2.4
Name: copycat-linux
Version: 1.0.2
Summary: Advanced Linux clipboard utility that bypasses paste restrictions using virtual keyboard typing
Author-email: Pink Pixel <admin@pinkpixel.dev>
Maintainer-email: Pink Pixel <admin@pinkpixel.dev>
License-Expression: Apache-2.0
Project-URL: Homepage, https://github.com/pinkpixel-dev/copycat
Project-URL: Documentation, https://github.com/pinkpixel-dev/copycat#readme
Project-URL: Changelog, https://github.com/pinkpixel-dev/copycat/blob/main/CHANGELOG.md
Project-URL: Issues, https://github.com/pinkpixel-dev/copycat/issues
Project-URL: Repository, https://github.com/pinkpixel-dev/copycat.git
Project-URL: Bug Reports, https://github.com/pinkpixel-dev/copycat/issues
Project-URL: Funding, https://www.buymeacoffee.com/pinkpixel
Keywords: clipboard,linux,productivity,automation,virtual-keyboard,paste-bypass,tkinter,gui
Classifier: Development Status :: 4 - Beta
Classifier: Intended Audience :: End Users/Desktop
Classifier: Intended Audience :: Developers
Classifier: Operating System :: POSIX :: Linux
Classifier: Programming Language :: Python
Classifier: Programming Language :: Python :: 3
Classifier: Programming Language :: Python :: 3.9
Classifier: Programming Language :: Python :: 3.10
Classifier: Programming Language :: Python :: 3.11
Classifier: Programming Language :: Python :: 3.12
Classifier: Programming Language :: Python :: 3.13
Classifier: Topic :: Utilities
Classifier: Topic :: Desktop Environment
Classifier: Topic :: System :: Systems Administration
Classifier: Environment :: X11 Applications
Requires-Python: >=3.9
License-File: LICENSE
Provides-Extra: tray
Requires-Dist: pystray>=0.19.5; extra == "tray"
Dynamic: license-file
